doc_control/__init__.py
doc_control/doc_control.py
midas_api/__init__.py
midas_api/midas_api.py
pymimi-0.0.1005.dist-info/licenses/LICENSE.txt
pymimi-0.0.1005.dist-info/METADATA
pymimi-0.0.1005.dist-info/WHEEL
pymimi-0.0.1005.dist-info/top_level.txt
pymimi-0.0.1005.dist-info/RECORD
