Metadata-Version: 2.4
Name: pymimi
Version: 0.0.1005
Summary: 这是一个适用于Midas Cvil NX二次开发库，旨在帮助摆脱繁琐的json编写
Home-page: https://github.com/ManiacasTraitor/Midas-Civil--PyMiMi
Author: ManiacsTraitor
Author-email: 2727671635@qq.com
Classifier: Programming Language :: Python :: 3
Classifier: License :: OSI Approved :: MIT License
Classifier: Operating System :: OS Independent
Requires-Python: >=3.6
License-File: LICENSE.txt
Requires-Dist: requests
Dynamic: author
Dynamic: author-email
Dynamic: classifier
Dynamic: description
Dynamic: home-page
Dynamic: license-file
Dynamic: requires-dist
Dynamic: requires-python
Dynamic: summary
